fastapi_users_ormar_extension/__init__.py
fastapi_users_ormar_extension/py.typed
fastapi_users_ormar_extension-0.3.0.dist-info/LICENSE
fastapi_users_ormar_extension-0.3.0.dist-info/METADATA
fastapi_users_ormar_extension-0.3.0.dist-info/WHEEL
fastapi_users_ormar_extension-0.3.0.dist-info/RECORD
